everyvoice/__init__.py
everyvoice/__main__.py
everyvoice/_version.py
everyvoice/cli.py
everyvoice/evaluation.py
everyvoice/exceptions.py
everyvoice/run_tests.py
everyvoice/base_cli/__init__.py
everyvoice/base_cli/callback.py
everyvoice/base_cli/checkpoint.py
everyvoice/base_cli/helpers.py
everyvoice/base_cli/interfaces.py
everyvoice/config/__init__.py
everyvoice/config/preprocessing_config.py
everyvoice/config/shared_types.py
everyvoice/config/text_config.py
everyvoice/config/type_definitions.py
everyvoice/config/utils.py
everyvoice/config/validation_helpers.py
everyvoice/dataloader/__init__.py
everyvoice/dataloader/imbalanced_sampler.py
everyvoice/demo/__init__.py
everyvoice/demo/app.py
everyvoice/model/__init__.py
everyvoice/model/utils.py
everyvoice/model/aligner/__init__.py
everyvoice/model/aligner/config.py
everyvoice/model/aligner/DeepForcedAligner/pyproject.toml
everyvoice/model/aligner/DeepForcedAligner/dfaligner/__init__.py
everyvoice/model/aligner/DeepForcedAligner/dfaligner/__main__.py
everyvoice/model/aligner/DeepForcedAligner/dfaligner/_version.py
everyvoice/model/aligner/DeepForcedAligner/dfaligner/cli.py
everyvoice/model/aligner/DeepForcedAligner/dfaligner/dataset.py
everyvoice/model/aligner/DeepForcedAligner/dfaligner/duration_extraction.py
everyvoice/model/aligner/DeepForcedAligner/dfaligner/model.py
everyvoice/model/aligner/DeepForcedAligner/dfaligner/utils.py
everyvoice/model/aligner/DeepForcedAligner/dfaligner/config/__init__.py
everyvoice/model/aligner/wav2vec2aligner/pyproject.toml
everyvoice/model/aligner/wav2vec2aligner/aligner/__init__.py
everyvoice/model/aligner/wav2vec2aligner/aligner/__main__.py
everyvoice/model/aligner/wav2vec2aligner/aligner/_version.py
everyvoice/model/aligner/wav2vec2aligner/aligner/classes.py
everyvoice/model/aligner/wav2vec2aligner/aligner/cli.py
everyvoice/model/aligner/wav2vec2aligner/aligner/heavy.py
everyvoice/model/aligner/wav2vec2aligner/aligner/utils.py
everyvoice/model/e2e/__init__.py
everyvoice-0.3.0.dist-info/METADATA
everyvoice-0.3.0.dist-info/WHEEL
everyvoice-0.3.0.dist-info/entry_points.txt
everyvoice-0.3.0.dist-info/licenses/LICENSE
everyvoice-0.3.0.dist-info/RECORD
