Metadata-Version: 2.4
Name: EveryVoice
Version: 0.3.0
Summary: Text-to-Speech Synthesis for the Speech Generation for Indigenous Language Education Small Teams Project
Project-URL: Homepage, https://github.com/EveryVoiceTTS/EveryVoice
Project-URL: Documentation, https://docs.everyvoice.ca
Project-URL: Repository, https://github.com/EveryVoiceTTS/EveryVoice
Project-URL: Issues, https://github.com/EveryVoiceTTS/EveryVoice/issues
Project-URL: Changelog, https://github.com/EveryVoiceTTS/EveryVoice/releases
Author-email: Aidan Pine <Aidan.Pine@nrc-cnrc.gc.ca>, Eric Joanis <Eric.Joanis@nrc-cnrc.gc.ca>, Marc Tessier <Marc.Tessier@nrc-cnrc.gc.ca>, Mengzhe Geng <Mengzhe.Geng@nrc-cnrc.gc.ca>, Samuel Larkin <Samuel.Larkin@nrc-cnrc.gc.ca>
Maintainer-email: Aidan Pine <Aidan.Pine@nrc-cnrc.gc.ca>, Eric Joanis <Eric.Joanis@nrc-cnrc.gc.ca>, Samuel Larkin <Samuel.Larkin@nrc-cnrc.gc.ca>
License: For everything but the exceptions listed below:
License-File: LICENSE
Keywords: CLI,TTS
Classifier: Development Status :: 4 - Beta
Classifier: Intended Audience :: Developers
Classifier: Intended Audience :: Education
Classifier: Intended Audience :: End Users/Desktop
Classifier: Intended Audience :: Other Audience
Classifier: Intended Audience :: Science/Research
Classifier: License :: OSI Approved :: MIT License
Classifier: Operating System :: MacOS
Classifier: Operating System :: MacOS :: MacOS X
Classifier: Operating System :: POSIX :: Linux
Classifier: Programming Language :: Python
Classifier: Programming Language :: Python :: 3
Classifier: Programming Language :: Python :: 3 :: Only
Classifier: Programming Language :: Python :: 3.10
Classifier: Programming Language :: Python :: 3.11
Classifier: Programming Language :: Python :: 3.12
Classifier: Programming Language :: Unix Shell
Classifier: Topic :: Multimedia :: Sound/Audio :: Speech
Classifier: Typing :: Typed
Requires-Python: <3.13,>=3.10
Requires-Dist: anytree>=2.12.1
Requires-Dist: click<8.2.0
Requires-Dist: clipdetect>=0.1.4
Requires-Dist: deepdiff>=6.5.0
Requires-Dist: einops==0.5.0
Requires-Dist: g2p~=2.0
Requires-Dist: gradio>=5.9.1
Requires-Dist: grapheme>=0.6.0
Requires-Dist: ipatok>=0.4.1
Requires-Dist: librosa==0.9.2
Requires-Dist: lightning>=2.0.0
Requires-Dist: loguru==0.6.0
Requires-Dist: matplotlib~=3.9.0
Requires-Dist: merge-args
Requires-Dist: nltk==3.9.1
Requires-Dist: numpy<2
Requires-Dist: packaging>=20.9
Requires-Dist: pandas~=2.0
Requires-Dist: panphon==0.20.0
Requires-Dist: protobuf~=4.25
Requires-Dist: pycountry==22.3.5
Requires-Dist: pydantic[email]<2.8.0,>=2.4.2
Requires-Dist: pympi-ling
Requires-Dist: pysdtw==0.0.5
Requires-Dist: pyworld-prebuilt==0.3.4.4
Requires-Dist: pyyaml>=5.1
Requires-Dist: questionary==1.10.0
Requires-Dist: readalongs>=1.2.0
Requires-Dist: simple-term-menu==1.5.2
Requires-Dist: tabulate==0.9.0
Requires-Dist: tensorboard>=2.14.1
Requires-Dist: torch==2.3.1
Requires-Dist: torchaudio==2.3.1
Requires-Dist: torchinfo==1.8.0
Requires-Dist: tqdm>=4.66.0
Requires-Dist: typer>=0.12.4
Requires-Dist: yaspin>=3.1.0
Provides-Extra: dev
Requires-Dist: black~=24.3; extra == 'dev'
Requires-Dist: coverage; extra == 'dev'
Requires-Dist: diff-cover; extra == 'dev'
Requires-Dist: flake8>=4.0.1; extra == 'dev'
Requires-Dist: gitlint-core>=0.19.0; extra == 'dev'
Requires-Dist: isort>=5.10.1; extra == 'dev'
Requires-Dist: jsonschema>=4.17.3; extra == 'dev'
Requires-Dist: mypy>=1.8.0; extra == 'dev'
Requires-Dist: pep440>=0.1.2; extra == 'dev'
Requires-Dist: playwright>=1.52.0; extra == 'dev'
Requires-Dist: pre-commit>=3.2.0; extra == 'dev'
Requires-Dist: types-pyyaml>=6.0.5; extra == 'dev'
Requires-Dist: types-requests>=2.27.11; extra == 'dev'
Requires-Dist: types-setuptools>=57.4.9; extra == 'dev'
Requires-Dist: types-tabulate==0.9.0; extra == 'dev'
Requires-Dist: types-tqdm<5.0,>=4.64; extra == 'dev'
Provides-Extra: docs
Requires-Dist: mike>=1.1.2; extra == 'docs'
Requires-Dist: mkdocs-click>=0.8.0; extra == 'docs'
Requires-Dist: mkdocs-macros-plugin>=1.0.4; extra == 'docs'
Requires-Dist: mkdocs-material>=9.2.5; extra == 'docs'
Requires-Dist: mkdocs-typer>=0.0.3; extra == 'docs'
Requires-Dist: mkdocs>=1.5.2; extra == 'docs'
Requires-Dist: mkdocstrings[python]>=0.22.0; extra == 'docs'
Provides-Extra: test
Requires-Dist: jsonschema>=4.17.3; extra == 'test'
Requires-Dist: pep440>=0.1.2; extra == 'test'
Requires-Dist: playwright>=1.52.0; extra == 'test'
Provides-Extra: torch
Requires-Dist: torch==2.3.1; (sys_platform == 'darwin') and extra == 'torch'
Requires-Dist: torchaudio==2.3.1; (sys_platform == 'darwin') and extra == 'torch'
